MANIFEST.in
README.md
requirements.txt
setup.py
flask_restframework/__init__.py
flask_restframework/adapters.py
flask_restframework/authentication_backend.py
flask_restframework/content_types.py
flask_restframework/decorators.py
flask_restframework/exception_handling.py
flask_restframework/exceptions.py
flask_restframework/fields.py
flask_restframework/filter_backends.py
flask_restframework/middlewares.py
flask_restframework/model_mixins.py
flask_restframework/pagination.py
flask_restframework/router.py
flask_restframework/validators.py
flask_restframework.egg-info/PKG-INFO
flask_restframework.egg-info/SOURCES.txt
flask_restframework.egg-info/dependency_links.txt
flask_restframework.egg-info/not-zip-safe
flask_restframework.egg-info/top_level.txt
flask_restframework/__pycache__/__init__.cpython-34.pyc
flask_restframework/__pycache__/__init__.cpython-35.pyc
flask_restframework/__pycache__/__init__.cpython-36.pyc
flask_restframework/__pycache__/authentication_backend.cpython-34.pyc
flask_restframework/__pycache__/authentication_backend.cpython-35.pyc
flask_restframework/__pycache__/decorators.cpython-34.pyc
flask_restframework/__pycache__/decorators.cpython-35.pyc
flask_restframework/__pycache__/decorators.cpython-36.pyc
flask_restframework/__pycache__/exception_handling.cpython-34.pyc
flask_restframework/__pycache__/exception_handling.cpython-35.pyc
flask_restframework/__pycache__/exceptions.cpython-34.pyc
flask_restframework/__pycache__/exceptions.cpython-35.pyc
flask_restframework/__pycache__/exceptions.cpython-36.pyc
flask_restframework/__pycache__/fields.cpython-34.pyc
flask_restframework/__pycache__/fields.cpython-35.pyc
flask_restframework/__pycache__/fields.cpython-36.pyc
flask_restframework/__pycache__/filter_backends.cpython-34.pyc
flask_restframework/__pycache__/filter_backends.cpython-35.pyc
flask_restframework/__pycache__/filter_backends.cpython-36.pyc
flask_restframework/__pycache__/middlewares.cpython-34.pyc
flask_restframework/__pycache__/middlewares.cpython-35.pyc
flask_restframework/__pycache__/model_mixins.cpython-34.pyc
flask_restframework/__pycache__/model_mixins.cpython-35.pyc
flask_restframework/__pycache__/model_resource.cpython-35.pyc
flask_restframework/admin/client/node_modules/jasmine-core/jasmine_core.egg-info/PKG-INFO
flask_restframework/admin/client/node_modules/jasmine-core/jasmine_core.egg-info/SOURCES.txt
flask_restframework/admin/client/node_modules/jasmine-core/jasmine_core.egg-info/dependency_links.txt
flask_restframework/admin/client/node_modules/jasmine-core/jasmine_core.egg-info/requires.txt
flask_restframework/admin/client/node_modules/jasmine-core/jasmine_core.egg-info/top_level.txt
