Metadata-Version: 1.1
Name: flask-restframework
Version: 0.2.1
Summary: Web APIs for Flask, made easy, inspired from Django DRF.
Home-page: https://github.com/sallyruthstruik/flask_restframework
Author: Stas Kaledin
Author-email: staskaledin@gmail.com
License: BSD
Platform: UNKNOWN
Classifier: Development Status :: 3 - Alpha
Classifier: Environment :: Web Environment
Classifier: Framework :: Flask
Classifier: Intended Audience :: Developers
Classifier: License :: OSI Approved :: BSD License
Classifier: Operating System :: OS Independent
Classifier: Programming Language :: Python
Classifier: Programming Language :: Python :: 2.7
Classifier: Programming Language :: Python :: 3.4
Classifier: Programming Language :: Python :: 3.5
Classifier: Topic :: Internet :: WWW/HTTP
